vision_agents/PROTOBUF_GENERATION.md
vision_agents/_generate_sfu_events.py
vision_agents/core/__init__.py
vision_agents/core/instructions.py
vision_agents/core/warmup.py
vision_agents/core/agents/__init__.py
vision_agents/core/agents/agent_launcher.py
vision_agents/core/agents/agent_types.py
vision_agents/core/agents/agents.py
vision_agents/core/agents/conversation.py
vision_agents/core/agents/events.py
vision_agents/core/agents/transcript_buffer.py
vision_agents/core/cli/__init__.py
vision_agents/core/cli/cli_runner.py
vision_agents/core/edge/__init__.py
vision_agents/core/edge/edge_transport.py
vision_agents/core/edge/events.py
vision_agents/core/edge/sfu_events.py
vision_agents/core/edge/types.py
vision_agents/core/events/__init__.py
vision_agents/core/events/base.py
vision_agents/core/events/manager.py
vision_agents/core/llm/__init__.py
vision_agents/core/llm/events.py
vision_agents/core/llm/function_registry.py
vision_agents/core/llm/llm.py
vision_agents/core/llm/llm_test.py
vision_agents/core/llm/llm_types.py
vision_agents/core/llm/realtime.py
vision_agents/core/llm/wrap_function.py
vision_agents/core/llm/wrap_method.py
vision_agents/core/mcp/__init__.py
vision_agents/core/mcp/mcp_base.py
vision_agents/core/mcp/mcp_manager.py
vision_agents/core/mcp/mcp_server_local.py
vision_agents/core/mcp/mcp_server_remote.py
vision_agents/core/mcp/tool_converter.py
vision_agents/core/observability/__init__.py
vision_agents/core/observability/agent.py
vision_agents/core/observability/collector.py
vision_agents/core/observability/metrics.py
vision_agents/core/processors/__init__.py
vision_agents/core/processors/base_processor.py
vision_agents/core/profiling/__init__.py
vision_agents/core/profiling/base.py
vision_agents/core/rag/__init__.py
vision_agents/core/rag/rag.py
vision_agents/core/stt/__init__.py
vision_agents/core/stt/events.py
vision_agents/core/stt/stt.py
vision_agents/core/tts/__init__.py
vision_agents/core/tts/events.py
vision_agents/core/tts/manual_test.py
vision_agents-0.2.10.dist-info/METADATA
vision_agents-0.2.10.dist-info/WHEEL
vision_agents-0.2.10.dist-info/RECORD
